CHANGELOG.rst
CREDITS.rst
LICENSE
MANIFEST.in
README.md
demo.py
setup.py
flask_mwoauth/__init__.py
flask_mwoauth.egg-info/PKG-INFO
flask_mwoauth.egg-info/SOURCES.txt
flask_mwoauth.egg-info/dependency_links.txt
flask_mwoauth.egg-info/requires.txt
flask_mwoauth.egg-info/top_level.txt
flask_mwoauth.egg-info/zip-safe