Metadata-Version: 1.1
Name: flask-mwoauth
Version: 0.3.70
Summary: Flask blueprint to connect to a MediaWiki OAuth server
Home-page: http://github.com/valhallasw/flask-mwoauth
Author: Merlijn van Deen
Author-email: valhallasw@arctus.nl
License: MIT
Platform: UNKNOWN
Classifier: Development Status :: 3 - Alpha
Classifier: Environment :: Web Environment
Classifier: License :: OSI Approved :: MIT License
Classifier: Operating System :: OS Independent
Classifier: Programming Language :: Python :: 2
Classifier: Programming Language :: Python :: 3
Classifier: Topic :: Internet :: WWW/HTTP :: Dynamic Content
Classifier: Topic :: Software Development :: Libraries :: Python Modules
